numdeclination/__init__.py
numdeclination/cases.py
numdeclination-0.0.1.0.dist-info/METADATA
numdeclination-0.0.1.0.dist-info/WHEEL
numdeclination-0.0.1.0.dist-info/top_level.txt
numdeclination-0.0.1.0.dist-info/RECORD
