Metadata-Version: 2.1
Name: numdeclination
Version: 0.0.1.0
Summary: Средство для склонения слов по числам
Home-page: UNKNOWN
Author: UNKNOWN
Author-email: UNKNOWN
License: UNKNOWN
Platform: UNKNOWN
